cldfviz/__init__.py
cldfviz/cli_util.py
cldfviz/colormap.py
cldfviz/glottolog.py
cldfviz/media.py
cldfviz/multiparameter.py
cldfviz/pdutils.py
cldfviz/template.py
cldfviz/text.py
cldfviz/tree.py
cldfviz/commands/__init__.py
cldfviz/commands/audiowordlist.py
cldfviz/commands/erd.py
cldfviz/commands/examples.py
cldfviz/commands/map.py
cldfviz/commands/network.py
cldfviz/commands/text.py
cldfviz/commands/tree.py
cldfviz/commands/treemap.py
cldfviz/map/__init__.py
cldfviz/map/base.py
cldfviz/map/leaflet.py
cldfviz/map/mpl.py
cldfviz/templates/audiowordlist/audiowordlist.html
cldfviz/templates/examples/examples.html
cldfviz/templates/map/README.md
cldfviz/templates/map/ecoregions.geojson.zip
cldfviz/templates/map/ecoregions.js
cldfviz/templates/map/leaflet.html
cldfviz/templates/text/BorrowingTable_detail.md
cldfviz/templates/text/CodeTable_detail.md
cldfviz/templates/text/CognateTable_detail.md
cldfviz/templates/text/CognateTable_index.md
cldfviz/templates/text/CognatesetTable_detail.md
cldfviz/templates/text/ContributionTable_detail.md
cldfviz/templates/text/ContributionTable_index.md
cldfviz/templates/text/EntryTable_detail.md
cldfviz/templates/text/ExampleTable_detail.md
cldfviz/templates/text/FormTable_detail.md
cldfviz/templates/text/LanguageTable_detail.md
cldfviz/templates/text/LanguageTable_index.md
cldfviz/templates/text/MediaTable_detail.md
cldfviz/templates/text/Metadata_detail.md
cldfviz/templates/text/ParameterTable_detail.md
cldfviz/templates/text/ParameterTable_index.md
cldfviz/templates/text/SenseTable_detail.md
cldfviz/templates/text/Source_detail.md
cldfviz/templates/text/Source_index.md
cldfviz/templates/text/ValueTable_detail.md
cldfviz/templates/text/property.md
cldfviz/templates/text/util.md
cldfviz-1.3.0.dist-info/LICENSE
cldfviz-1.3.0.dist-info/METADATA
cldfviz-1.3.0.dist-info/WHEEL
cldfviz-1.3.0.dist-info/entry_points.txt
cldfviz-1.3.0.dist-info/top_level.txt
cldfviz-1.3.0.dist-info/RECORD
