Metadata-Version: 2.1
Name: cldfviz
Version: 1.3.0
Summary: A cldfbench plugin to create vizualisations of CLDF datasets
Home-page: https://github.com/cldf/cldfviz
Author: Robert Forkel
Author-email: dlce.rdm@eva.mpg.de
License: Apache 2.0
Project-URL: Bug Tracker, https://github.com/cldf/cldfviz/issues
Keywords: cldfbench
Platform: any
Classifier: Development Status :: 5 - Production/Stable
Classifier: Intended Audience :: Developers
Classifier: Natural Language :: English
Classifier: Operating System :: OS Independent
Classifier: Programming Language :: Python :: 3
Classifier: Programming Language :: Python :: 3.8
Classifier: Programming Language :: Python :: 3.9
Classifier: Programming Language :: Python :: 3.10
Classifier: Programming Language :: Python :: 3.11
Classifier: Programming Language :: Python :: 3.12
Classifier: License :: OSI Approved :: Apache Software License
Requires-Python: >=3.8
License-File: LICENSE
Requires-Dist: attrs
Requires-Dist: cldfbench (>=1.11.0)
Requires-Dist: clldutils (>=3.17)
Requires-Dist: jinja2
Requires-Dist: matplotlib
Requires-Dist: newick (>=1.6)
Requires-Dist: numpy
Requires-Dist: packaging
Requires-Dist: pycldf (>=1.32.0)
Requires-Dist: pyglottolog
Requires-Dist: termcolor
Requires-Dist: toytree (~=2.0.1)
Requires-Dist: tqdm
Provides-Extra: cartopy
Requires-Dist: cartopy ; extra == 'cartopy'
Requires-Dist: scipy ; extra == 'cartopy'
Requires-Dist: shapely ; extra == 'cartopy'
Provides-Extra: dev
Requires-Dist: build ; extra == 'dev'
Requires-Dist: flake8 ; extra == 'dev'
Requires-Dist: twine ; extra == 'dev'
Requires-Dist: wheel ; extra == 'dev'
Provides-Extra: lingtreemaps
Requires-Dist: biopython ; extra == 'lingtreemaps'
Requires-Dist: lingtreemaps ; extra == 'lingtreemaps'
Requires-Dist: pandas ; extra == 'lingtreemaps'
Requires-Dist: pyyaml ; extra == 'lingtreemaps'
Requires-Dist: shapely ; extra == 'lingtreemaps'
Provides-Extra: network
Requires-Dist: networkx ; extra == 'network'
Provides-Extra: test
Requires-Dist: coverage (>=4.2) ; extra == 'test'
Requires-Dist: networkx ; extra == 'test'
Requires-Dist: pytest-cov ; extra == 'test'
Requires-Dist: pytest-mock ; extra == 'test'
Requires-Dist: pytest (>=5) ; extra == 'test'
Requires-Dist: requests-mock ; extra == 'test'
